.gitignore
.travis.yml
LICENSE
Makefile
README.md
requirements.txt
setup.py
test_requirements.txt
mozilla_taarlite.egg-info/PKG-INFO
mozilla_taarlite.egg-info/SOURCES.txt
mozilla_taarlite.egg-info/dependency_links.txt
mozilla_taarlite.egg-info/not-zip-safe
mozilla_taarlite.egg-info/requires.txt
mozilla_taarlite.egg-info/top_level.txt
scripts/pregenerate.py
taar_lite/__init__.py
taar_lite/recommenders/__init__.py
taar_lite/recommenders/cache.py
taar_lite/recommenders/guid_based_recommender.py
tests/__init__.py
tests/conftest.py
tests/test_cache.py
tests/test_guid_based_recommender.py
tests/test_logging.py