Metadata-Version: 1.1
Name: mozilla-taarlite
Version: 0.1.11
Summary: Telemetry-Aware Addon Recommender Lite
Home-page: https://github.com/mozilla/taar-lite
Author: Mozilla Foundation
Author-email: fx-data-dev@mozilla.org
License: MPL 2.0
Platform: UNKNOWN
Classifier: Development Status :: 3 - Alpha
Classifier: Environment :: Web Environment :: Mozilla
Classifier: Intended Audience :: Developers
Classifier: License :: OSI Approved :: Mozilla Public License 2.0 (MPL 2.0)
Classifier: Programming Language :: Python
Classifier: Programming Language :: Python :: 3
Classifier: Programming Language :: Python :: 3.5
Classifier: Topic :: Internet :: WWW/HTTP
Classifier: Topic :: Scientific/Engineering :: Information Analysis
